MANIFEST.in
README.md
setup.cfg
setup.py
keeb/__init__.py
keeb/main.py
keeb/sounds/gateron-red/'.mp3
keeb/sounds/gateron-red/,.mp3
keeb/sounds/gateron-red/-.mp3
keeb/sounds/gateron-red/..mp3
keeb/sounds/gateron-red/0.mp3
keeb/sounds/gateron-red/1.mp3
keeb/sounds/gateron-red/2.mp3
keeb/sounds/gateron-red/3.mp3
keeb/sounds/gateron-red/4.mp3
keeb/sounds/gateron-red/5.mp3
keeb/sounds/gateron-red/6.mp3
keeb/sounds/gateron-red/7.mp3
keeb/sounds/gateron-red/8.mp3
keeb/sounds/gateron-red/9.mp3
keeb/sounds/gateron-red/;.mp3
keeb/sounds/gateron-red/=.mp3
keeb/sounds/gateron-red/BACKSLASH.mp3
keeb/sounds/gateron-red/BACKSPACE.mp3
keeb/sounds/gateron-red/CAPS.mp3
keeb/sounds/gateron-red/CMD.mp3
keeb/sounds/gateron-red/ENTER.mp3
keeb/sounds/gateron-red/ESC.mp3
keeb/sounds/gateron-red/FN.mp3
keeb/sounds/gateron-red/LALT.mp3
keeb/sounds/gateron-red/LCTRL.mp3
keeb/sounds/gateron-red/LSHIFT.mp3
keeb/sounds/gateron-red/MENU.mp3
keeb/sounds/gateron-red/RALT.mp3
keeb/sounds/gateron-red/RCTRL.mp3
keeb/sounds/gateron-red/RSHIFT.mp3
keeb/sounds/gateron-red/SLASH.mp3
keeb/sounds/gateron-red/SPACE.mp3
keeb/sounds/gateron-red/TAB.mp3
keeb/sounds/gateron-red/[.mp3
keeb/sounds/gateron-red/].mp3
keeb/sounds/gateron-red/a.mp3
keeb/sounds/gateron-red/b.mp3
keeb/sounds/gateron-red/c.mp3
keeb/sounds/gateron-red/d.mp3
keeb/sounds/gateron-red/e.mp3
keeb/sounds/gateron-red/f.mp3
keeb/sounds/gateron-red/g.mp3
keeb/sounds/gateron-red/h.mp3
keeb/sounds/gateron-red/i.mp3
keeb/sounds/gateron-red/j.mp3
keeb/sounds/gateron-red/k.mp3
keeb/sounds/gateron-red/l.mp3
keeb/sounds/gateron-red/m.mp3
keeb/sounds/gateron-red/n.mp3
keeb/sounds/gateron-red/o.mp3
keeb/sounds/gateron-red/p.mp3
keeb/sounds/gateron-red/q.mp3
keeb/sounds/gateron-red/r.mp3
keeb/sounds/gateron-red/s.mp3
keeb/sounds/gateron-red/t.mp3
keeb/sounds/gateron-red/u.mp3
keeb/sounds/gateron-red/v.mp3
keeb/sounds/gateron-red/w.mp3
keeb/sounds/gateron-red/x.mp3
keeb/sounds/gateron-red/y.mp3
keeb/sounds/gateron-red/z.mp3
keebsound.egg-info/PKG-INFO
keebsound.egg-info/SOURCES.txt
keebsound.egg-info/dependency_links.txt
keebsound.egg-info/entry_points.txt
keebsound.egg-info/requires.txt
keebsound.egg-info/top_level.txt